MANIFEST.in
README.rst
setup.py
phabricator/__init__.py
phabricator/base/APIRequest.py
phabricator/base/__init__.py
phabricator/base/session.py
phabricator/config/__init__.py
phabricator/config/settings_sample.py
phabricator/paste/__init__.py
phabricator/paste/query.py
phabricator_python.egg-info/PKG-INFO
phabricator_python.egg-info/SOURCES.txt
phabricator_python.egg-info/dependency_links.txt
phabricator_python.egg-info/not-zip-safe
phabricator_python.egg-info/requires.txt
phabricator_python.egg-info/top_level.txt