Metadata-Version: 1.1
Name: phabricator-python
Version: 0.3
Summary: Python Based Phabricator API Bindings
Home-page: http://github.com/creativepsyco/python-phabricator
Author: Mohit Kanwal
Author-email: mohit.kanwal@gmail.com
License: GPL v2
Platform: UNKNOWN
Classifier: Intended Audience :: Developers
Classifier: Intended Audience :: System Administrators
Classifier: Operating System :: OS Independent
Classifier: Topic :: Software Development
